DataSanitiser/__init__.py
DataSanitiser/utils/Structured.py
DataSanitiser/utils/__init__.py
DataSanitiser/utils/huetoolkit.py
DataSanitiser/utils/iotoolkit.py
DataSanitiser/utils/pdtoolkit.py
DataSanitiser-1.0.9.2.dist-info/LICENSE
DataSanitiser-1.0.9.2.dist-info/METADATA
DataSanitiser-1.0.9.2.dist-info/WHEEL
DataSanitiser-1.0.9.2.dist-info/top_level.txt
DataSanitiser-1.0.9.2.dist-info/RECORD
